README.md
setup.py
torchtensornetwork/__init__.py
torchtensornetwork.egg-info/PKG-INFO
torchtensornetwork.egg-info/SOURCES.txt
torchtensornetwork.egg-info/dependency_links.txt
torchtensornetwork.egg-info/requires.txt
torchtensornetwork.egg-info/top_level.txt
torchtensornetwork/embeddings/__init__.py
torchtensornetwork/embeddings/qembedding.py
torchtensornetwork/gates/__init__.py
torchtensornetwork/gates/qcircuit.py
torchtensornetwork/gates/qgate.py
torchtensornetwork/gates/qmath.py
torchtensornetwork/gates/qoperator.py
torchtensornetwork/layers/__init__.py
torchtensornetwork/layers/qlayer.py
torchtensornetwork/layers/qlayers.py
torchtensornetwork/nn/__init__.py
torchtensornetwork/nn/modules/__init__.py
torchtensornetwork/nn/modules/qconv.py
torchtensornetwork/nn/modules/qpooling.py
torchtensornetwork/nn/modules/qrnn.py
torchtensornetwork/nn/modules/qtransformer.py