Metadata-Version: 1.0
Name: torchtensornetwork
Version: 0.0.1
Summary: tensor network for torch
Home-page: UNKNOWN
Author: TuringQ
Author-email: UNKNOWN
License: UNKNOWN
Platform: UNKNOWN
